dang_sqlfluffer/__init__.py
dang_sqlfluffer/__main__.py
dang_sqlfluffer/cli.py
dang_sqlfluffer/config/my.sqlfluff
dang_sqlfluffer-0.1.1.dist-info/LICENSE
dang_sqlfluffer-0.1.1.dist-info/METADATA
dang_sqlfluffer-0.1.1.dist-info/WHEEL
dang_sqlfluffer-0.1.1.dist-info/entry_points.txt
dang_sqlfluffer-0.1.1.dist-info/top_level.txt
dang_sqlfluffer-0.1.1.dist-info/RECORD
