Metadata-Version: 2.1
Name: dang-sqlfluffer
Version: 0.1.1
Summary: my convenient opinionated wrapper around sqlfluff
Author: Dan Nguyen
License: Apache-2.0
Project-URL: Homepage, https://github.com/dannguyen/dang-sqlfluffer
Project-URL: Changelog, https://github.com/dannguyen/dang-sqlfluffer/releases
Project-URL: Issues, https://github.com/dannguyen/dang-sqlfluffer/issues
Project-URL: CI, https://github.com/dannguyen/dang-sqlfluffer/actions
Classifier: License :: OSI Approved :: Apache Software License
Requires-Python: >=3.10
License-File: LICENSE
Requires-Dist: click
Provides-Extra: test
Requires-Dist: pytest; extra == "test"
